{
    "id": 547,
    "url": "https://moscow.drugiegoroda.ru/attractions/27551-velotrek-krylatskoe/",
    "title": "Велотрек «Крылатское»",
    "subtitle": "Спортивное сооружение в Москве, в районе Крылатское",
    "description": "Построен в 1979 году к Олимпийским играм 1980 года по проекту авторского коллектива, возглавляемого архитекторами Н. И. Ворониной и А. Г. Оспенниковым.\nВелотрек расположен на Крылатской улице, между Крылатскими холмами и Гребным каналом.\nБольшепролётное сооружение имеет в плане форму эллипса с размерами осей 168 и 138 м. Пролёт велотрека длиной 168 метров перекрыт двумя парами наклонных арок, соединённых мембраной из рулонной стали толщиной 4 мм.\nПроект велотрека разработан в Московском научно-исследовательском и проектном институте объектов культуры, отдыха, спорта и здравоохранения авторским коллективом, в который вошли архитекторы Н. И. Воронина и А. Г. Оспенников; инженеры конструкторы: В. В. Ханджи, Ю. С. Родиченко, В. А. Бородин, И. В. Лисицин, М. В. Савицкий; технолог А. В. Зыченков; авторы зон архитекторы А. Р. Воронцов, Т. М. Завалищина, В. В. Рубцов, Л. М. Пивненко.\nС помощью ЦНИИСК им. В. А. Кучеренко были разработаны конструкции (д.т.н. В. Трофимов, к.т.н. Л. Гольденберг, к.т.н. П. Еремеев).\nИнститут ВНИПИ «Промстальконструкция» разработал проект монтажа.\nБлагодаря геометрии трека можно развить скорость до 90 км/час. Трековая дорожка имеет длину 333,33 м, ширину — 10 м; прямые участки, имеющие наклон 11°, не превышают 37 м, виражи подняты под углом 42° и имеют радиус 33 м.\nДорожка покрыта древесиной сибирской лиственницы. К моменту проведения Олимпийских игр 1980 года трек был одним из самых быстрых в мире, во время олимпийских соревнований на нём был установлено 13 мировых рекордов.\nЗа 20 лет на велотреке «Крылатское», входившем в пятёрку лучших велодромов в мире, было поставлено 200 мировых и европейских рекордов.\nВнутри трека уложено синтетическое покрытие, на нём можно проводить соревнования по мини-футболу, гандболу, лёгкой атлетике, теннису, ракетлону, настольному теннису.\nДве трибуны для зрителей (26 м высотой, по 3000 мест каждая) расположены параллельно прямым участкам дорожки трека.\n",
    "workingTime": "",
    "contacts": "Россия, Москва,Крылатская ул., д. 10",
    "price": "",
    "location": "",
    "photos": [
        {
            "title": "Велотрек в Крылатском. Спортивный комплекс был построен специально для Игр",
            "name": "46113-Krylatsky_Olympic_Velodrome-f-376x196.jpg"
        },
        {
            "title": "Велотрек на реверсе памятной золотой 100-рублёвой монеты",
            "name": "50825-RR3217-0008R-1024x1024.png"
        }
    ]
}