{
    "id": 340,
    "url": "https://moscow.drugiegoroda.ru/attractions/27606-osobnyak-saarbekova/",
    "title": "Особняк Саарбекова",
    "subtitle": "Известен как второе по времени произведение модерна в Москве и одно из ранних сооружений в этом стиле в России",
    "description": "Особняк М. С. Саарбекова — жилой дом на Поварской улице в Москве, построенный в 1899—1900 годах по проекту архитектора Льва Кекушева, при участии его помощника Сергея Шуцмана.\nИзвестен как второе по времени произведение модерна в Москве и одно из ранних сооружений в этом стиле в России. Имеет статус объекта культурного наследия регионального значения.\nДо октябрьской революции дом принадлежал Моисею Семёновичу Саарбекову — богатому московскому купцу армянского происхождения, по имени которого здание и вошло в историю архитектуры; здесь же располагались конторы принадлежавших Саарбекову предприятий. В 1920–1940 годах особняк занимала Литовская дипломатическая миссия во главе с известным поэтом Серебряного века Юргисом Балтрушайтисом. Позднее в здании разместилось представительство Литовской СССР, а с начала 1990-х годов здесь находится Культурный центр Литовской республики «Дом Балтрушайтиса».\nФасад здания, «зажатый» с двух сторон высокими соседними домами, отличает редкая для времени его постройки лаконичность декоративного оформления, главной темой которого являются выразительно прорисованные арочные обрамления окон, парадного входа и въезда во двор.\nВладение, которое занимает современное здание, сложилось во второй половине XVIII века. В начале XIX века по линии Поварской улицы стоял небольшой деревянный дом со служебными постройками во дворе, принадлежавший капитанской дочери Варваре Михайловне Лаухиной.\nВо время пожара 1812 года все постройки усадьбы сгорели. Восстанавливать владение начали после 1815 года — выстроили два новых жилых одноэтажных дома в ампирных формах, флигель вдоль северной границы участка и хозяйственные строения по боковым сторонам.\nВ 1822 году в доме Лаухиной останавливался отец М. Ю. Лермонтова «отставной корпусной капитан» Ю. П. Лермонтов, приехавший в Москву к родственникам. Весной 1828 года один из домов Лаухиной сняла бабушка Лермонтова — Е. А. Арсеньева, которая поселилась здесь вместе со своим 13-летним внуком и его товарищем по Тарханам Давыдовым. В этом доме Лермонтов написал первую поэму «Индианка» и начал издавать рукописный журнал «Утренняя Заря». После того как к проживающим присоединился П. П. Шан-Гирей с сыном Акимом, дом стал тесен, и осенью того же года Арсеньева переехала в соседнее владение, принадлежавшее вдове майора В. Я. Костомаровой (на месте современного № 26).\nВ 1841 году, когда участок перешёл во владение отставного майора графа А. И. Маркова, одноэтажные дома надстроили мезонинами. В 1860-х годах хозяйкой участка стала капитанша Е. П. Хвощинская, которая возвела вдоль улицы ещё одно каменное здание и переделала фасады построек в духе эклектики.\nВо второй четверти XIX века усадьба ещё несколько раз меняла владельцев, пока в 1899 году у мещанина П. И. Шведкова её не купил Моисей Семёнович Саарбеков (1855–после 1917) — потомственный почётный гражданин, богатый купец армянского происхождения. Саарбеков приходился зятем московской семьи Лианозовых, в долях с представителями которой владел Южно-Каспийским рыболовным промыслом, входил в состав правления Товарищества «Лианозова Г. М. Сыновей», занимавшегося нефтяным промыслом, владел химическим заводов за Рогожской заставой на Владимирском тракте.\nПо прошению Саарбекова в Московскую городскую управу от 19 мая 1899 года прежние постройки снесли, и хозяин участка заказал проект нового особняка гражданскому инженеру Льву Кекушеву. На утверждение в управу были поданы чертежи плана и эскиз фасада, которые выполнил и подписал ближайший помощник Кекушева — Сергей Шуцман.\nОднако постройка была осуществлена по другому проекту, авторство которого принадлежит Кекушеву, при участии Шуцмана. Возможно, в проектировании и строительстве особняка принимал участие и другой помощник зодчего — Иван Фомин, один из крупнейших русских архитекторов XX века, в 1899—1901 годах работавший в бюро Кекушева.\nВероятно, по желанию заказчика дом изначально должен был выполнять не только жилую, но и конторскую функцию, что и было учтено архитектором при проектировании внутренней структуры и внешнего облика здания.\nМоисей Саарбеков не только поселился в особняке, но и разместил здесь свои конторы — химического завода и промыслового предприятия. Саарбеков принадлежал к просвещённому купечеству — занимался благотворительностью, знал несколько языков и, вероятно, следил за европейской модой, где набирал популярность новый стиль, позднее получивший в России название модерн.\nВместе с тем Моисея Семёновича отличала чрезмерная экономность, которая нередко приводила к курьёзам. По легенде, когда у купца обнаружили жёлчнокаменную болезнь, он наотрез отказался лечь в больницу и велел сделать операцию прямо на дому, а чтобы пыль от проезжавших экипажей не вызвала осложнений, сначала приказал заасфальтировать Поварскую, а затем и вовсе перекрыть по ней движение. Хирург запросил за услуги три тысячи рублей, но Саарбеков предложил платить за каждый извлечённый камень — по тысяче рублей. В результате успешно проведённой операции у купца извлекли сорок мелких камней, а так как их размер изначально не оговаривался, Моисею Семёновичу пришлось выложить врачу баснословную по тем временам сумму — сорок тысяч рублей.\nПоследнее упоминание Саарбекова как хозяина особняка на Поварской улице содержится в адресной и справочной книге «Вся Москва» на 1917 год — на тот момент Моисей Семёнович служил в Лазаревском институте восточных языков.\nПосле октябрьской революции богатые особняки на Поварской улице национализировали и многие из них отдали под размещение дипломатических миссий. В 1920—1940 годах бывший особняк Саарбекова занимало дипломатическое представительство Литвы — специальная миссия, затем посольство в Советской России и СССР. Чрезвычайным и полномочным послом Литовской республики в 1922—1939 годах являлся поэт-символист Юргис Балтрушайтис, который работал и некоторое время жил в этом доме. Позднее, вплоть до начала 1990-х годов, здание занимало представительство Литовской СССР, при котором действовало общежитие для приезжающих. Во время Великой Отечественной войны в доме жил литовский писатель А. Венцлова, оставивший об этом свои воспоминания.\nВ 1992—1995 годах несколько комнат особняка занимала литовская средняя школа — в начале негосударственная, а с 1994 года получившая название «Шальтинелис» («Родничок») и преобразованная в государственную школу № 1247. В настоящее время в здании размещается Центр культурных проектов Литовской республики «Дом Балтрушайтиса». Здесь проходят литературные вечера, конференции, выставки художников и фотомастеров, выступают музыкальные коллективы. С 1990-х годов каждую последнюю декаду мая в особняке проводят международную научную конференцию, посвящённую Юргису Балтрушайтису и Серебряному веку. В особняке размещается резиденция атташе по культуре посольства Литовской республики; эту должность в 1996—2011 годах занимал Юозас Будрайтис.\nВ 1993 году на фасаде здания установили мемориальную доску в память о Ю. Балтрушайтисе. В 2009 году особняк М. С. Саарбекова принят под государственную охрану в качестве объекта культурного наследия регионального значения.\nЗаконченный строительством в 1900 году особняк М. С. Саарбекова стал второй по времени появления московской постройкой в стиле модерн и одним из первых сооружений в этом стиле в России. Первым произведением модерна в Москве принято считать построенный Кекушевым за год до этого особняк Листа, при проектировании которого зодчий выработал ряд авторских приёмов, неоднократно использованных им позднее в других своих произведениях, в том числе в особняке Саарбекова. Новый особняк на Поварской сразу же был высоко оценен профессионалами за редкую для того времени рафинированность форм. Приложение к журналу «Зодчий» «Неделя строителя» сообщало:\n«Двухэтажный дом-особняк на Поварской, построенный гражданским инженером Л. Кекушевым, вновь свидетельствует о выдающемся таланте этого зодчего. Дом выдержан в простом «Style nouveu» крайнего направления, не без дорогостоящих вычур».\nВыполненное из кирпича двухэтажное здание с полуподвалом поставлено по красной линии Поварской улицы; задняя, не видимая с улицы половина дома частично увеличена по высоте до трёх этажей. В отличие от других особняков Кекушева — Листа, Понизовского, Миндовского, Носова, трактованных автором как трёхмерная структура, эта постройка зодчего строго фасадна, что объясняется изначальной формой и размером выделенного под строительство участка. Вынужденную плоскостность архитектурной композиции Кекушев преодолел изобретательной пластикой фасада и значительным выносом кровли, трактованной как козырёк.\nТщательная прорисовка криволинейных дверных полотнищ и обрамлений, оконных проёмов и наличников является одним из характерных приёмов Кекушева. По мнению исследователя архитектуры модерна Марии Нащокиной, этот приём достиг совершенства в трёх постройках зодчего — особняке Саарбекова, собственном особняке и доходном доме на Остоженке, при этом в особняке Саарбекова арочные обрамления окон, входа и проезда во двор стали главной пластической темой фасада.\nОсобенно выразительно подчёркнут расположенный в левой части здания парадный вход, выделенный ризалитом, увенчанным высоким аттиком с тремя рядами мелких убывающих по высоте фигурных ниш и проёмов. Подобная асимметрия фасада сообщает архитектурной композиции некоторый динамизм, который усиливался за счёт первоначального заполнения входного портала, состоявшего из двух окон и дверного проёма, разделённых широкими каменными перемычками. В оформлении обрамления окна над парадным входом и фланкирующих его колонок угадываются восточные мотивы, что, возможно, объясняется происхождением заказчика. Как и в особняке Листа, деревянные переплёты некоторых окон снабжены снаружи сильно выступающими стилизованными ордерными элементами — миниатюрными приставными колонками.\nВ расположенный позади особняка небольшой двор ведёт проезд в правой части здания, оформленный как арочная галерея, накрытая четырьмя вспарушенными сводами; первоначально в центре каждой купольной ячейки висели фонари, подчёркивающие в тёмное время суток перспективу уходящих в глубь сводов. Проезд во двор закрывают створки кованых ворот, в орнаменте которых Кекушев использовал мотив завитка спирали, нарисованный в более спокойной манере, чем в лестничных ограждениях особняка\nВ отличие от уличного фасада здания, его дворовые стены полностью лишены отделки — необработанными остались даже обрамления окон. Судя по характеру кирпичной кладки, штукатурка предполагалась и здесь, что не было осуществлено, вероятно, по экономическим соображениям заказчика.\nПарадный вход ведёт на второй и третий этажи особняка, первоначально бывшие жилыми. Сразу за входом находится небольшой вестибюль, перекрытый высоким крестовым сводом; помещение освещается арочным окном, его стены обработаны горизонтальным рустом с выступающими поверхностями отдельных «блоков», а пол покрыт в шахматном порядке светлыми и тёмно-серыми керамическими плитками. На первый уровень ведёт короткая каменная лестница с двумя бо́льшими по длине скруглёнными забежными ступенями и кованным ограждением с орнаментом, стилизующим завиток спирали; верхняя площадка лестницы обращена ко входу небольшим балконом. Арочным проёмом эта площадка соединена с квадратным в плане монументальным пространством парадной лестницы, декорированным так же, как и вестибюль, и освещённом большим плоским квадратным фонарём верхнего света. Приём освещения верхним светом был распространён в сооружениях начала XX века, в том числе активно использовался Кеушевым в крупных жилых и общественных зданиях, однако в особняках он встречается довольно редко — по мнению М. В. Нащокиной, наиболее яркими примерами могут служить окна верхнего света в шехтелевском особняке С. П. Рябушинского и в особняке М. С. Саарбекова.\nНа втором этаже располагались главные парадные помещения дома, в оформлении которых Кекушев использовал те же декоративные приёмы, что и в особняке Листа — большой зал, кабинет хозяина (на фасаде он отмечен крупным окном над входом) и комната окнами во двор, первоначально бывшая, вероятно, столовой. Пространственные характеристики этих помещений остались в основном без изменений, однако декоративное убранство комнат большей частью утрачено. В кабинете сохранился угловой камин, выполненный из чёрного мрамора, с зеркалом в лепной раме над ним; из украшений зала, первоначально разделённого на два помещения (одно из них, вероятно, было гостиной), до наших дней дошли тянутые карнизы и лепные потолочные розетки; в столовой (?) сохранились тёмные деревянные потолочные балки, между которыми, возможно, располагались живописные вставки, ныне утраченные или закрашенные. В невысоком третьем этаже, видимом лишь со двора, находились личные покои Саарбекова. На обоих жилых этажах здания сохранились деревянные межкомнатные двери, дубовые оконные рамы с оригинальной металлической фурнитурой и несколько светильников, включая украшающую парадную лестницу скульптуру-светильник работы Феликса Шарпантье.\nВ проездной арке устроен ещё один вход в здание, через который посетители попадали в расположенные на первом этаже (бельэтаже) конторские помещения предприятий Саарбекова. Рядом со входом располагается помещение, первоначально предназначавшееся для привратника. В полуподвальном этаже находились подсобные помещения, дворницкая и прачечная. Все этажи связывает чёрная двухмаршевая лестница, расположенная в задней части особняка.\nВ 1905 году гражданский инженер В. А. Властов осуществил в особняке ряд внутренних работ; он же переделал конструкцию балкона в вестибюле, заменив деревянные балки на железные, несколько изменил задний фасад и возвёл во дворе каменные одноэтажные служебные постройки — конюшни и каретный сарай. В 1914 году дворовые постройки частично надстроили вторым этажом по проекту архитектора С. А. Власьева. Возможно, во время производства этих работ Властов и Власьев были сотрудниками архитектурного бюро Кекушева. В советское время конюшни и каретный сарай приспособили под автомобильные гаражи.\nГрадостроительное восприятие особняка существенно изменилось после возведения в 1910-х годах по линии улицы двух соседних высоких доходных домов — № 22 графини А. А. Милорадович (1912, архитектор Р. И. Клейн) и № 26 И. С. Баскакова (1914, архитектор О. Г. Пиотрович).\nОтделка уличного фасада постройки дошла до наших дней без существенных изменений. Негативно на архитектурной композиции здания отразилась произведённая в 1930-х (?) годах замена эффектной асимметричной композиции входа на ныне существующую примитивную деревянную раму с симметричными дверными полотнищами.\n<img src=\"http://ru.wikipedia.org/wiki/Special:CentralAutoLogin/start?type=1x1\" alt=\"\" title=\"\" width=\"1\" height=\"1\" style=\"border: none; position: absolute;\" />\n",
    "workingTime": "24/7, внешний осмотр",
    "contacts": "Россия, Москва, Поварская улица, 24, стр. 1",
    "price": "бесплатно",
    "location": "",
    "photos": [
        {
            "title": " Общий вид уличного фасада",
            "name": "51074-Povarskaya_24_Old_Lithuanian_Mission-1024x735.jpg"
        },
        {
            "title": "Е.&nbsp;А.&nbsp;Арсеньева, бабушка М.&nbsp;Ю.&nbsp;Лермонтова",
            "name": "51075-_._.__.._-796x1024.jpg"
        },
        {
            "title": "Л. Н. Кекушев. Фото 1907 г.",
            "name": "40886-__-f-376x436.jpg"
        },
        {
            "title": "Юргис Балтрушайтис",
            "name": "51077-JurgisBaltrusaitis-870x1024.jpg"
        },
        {
            "title": "В особняке М. С. Саарбекова. Ордерные элементы оконных переплётов в постройках Л. Н. Кекушева",
            "name": "51078-____-1024x661.jpg"
        },
        {
            "title": "В особняке О. А. Листа. Ордерные элементы оконных переплётов в постройках Л. Н. Кекушева",
            "name": "51079-____-1024x677.jpg"
        },
        {
            "title": "Оформление колонки над парадным входом",
            "name": "51080-___-666x1024.jpg"
        }
    ]
}