{
    "id": 208,
    "url": "https://moscow.drugiegoroda.ru/attractions/16490-garazh-gosplana/",
    "title": "Гараж Госплана",
    "subtitle": "Последнее по времени постройки из сохранившихся архитектурных сооружений К. С. Мельникова",
    "description": "Здание гаража на Авиамоторной улице в Москве, построенное в 1936 году по проекту выдающегося архитектора Константина Мельникова в соавторстве с архитектором В. И. Курочкиным для автомобилей Госплана СССР (в момент строительства — Государственная плановая комиссия при Совнаркоме СССР).\nКак и в построенном двумя годами ранее гараже Интуриста, рабочие чертежи здания были выполнены В. И. Курочкиным — архитектором архитектурно-проектной мастерской Моссовета № 7, возглавляемой К. С. Мельниковым. В отличие от Бахметьевского гаража и гаража на Новорязанской улице, целиком выполненных по проекту К. С. Мельникова, гараж Госплана требовал лишь «архитектурного оформления» фасадов для спроектированных инженерами-технологами типовых объёмно-конструктивных решений.\nТехнологической сути <…> я почти не касался, — вспоминал в 1965 году Константин Мельников, — предоставив вести это, а также и разработку рабочих чертежей своему весьма исполнительному сподвижнику архитектору В. И. Курочкину, занявшись сам рисовкой архитектуры внешних форм…\nОдноэтажное помещение для автомашин освещается большим выходящим на сторону Авиамоторной улицы круглым окном.\nФасад четырёхэтажного корпуса мастерских подчёркнут вертикальными каннелюрами.\nОдин «глаз», смещённый с центра к высокому объёму административного корпуса с узким прорезом трубы, — писал К. С. Мельников, — и я обрёл связь «формалистического» подхода с самой сущностью из мира прекрасного.\nВ 1955 году на территорию гаража и на соседние с ним участки был переведён 8-й таксомоторный парк г. Москвы. В 1995 году парк был преобразован в ОАО «Легавтотранссервис-8». В настоящее время таксомоторная компания работает под маркой «Старое доброе такси» и выполняет услуги по перевозке пассажиров и ремонту автомашин отечественного производства.\nВ 1990 году, в связи со 100-летием со дня рождения К. С. Мельникова, гараж Госплана включён в Список объектов культурного наследия Москвы регионального значения. В 1997 году было принято Постановление Московской городской думы, которым здание гаража Госплана было отнесено к перечню памятников истории и культуры, разрешённых к приватизации.\n16 января 2013 года гараж сгорел.\n\n",
    "workingTime": "24/7, внешний осмотр",
    "contacts": "Москва, Авиамоторная ул., 63 строение 1",
    "price": "бесплатно",
    "location": "",
    "photos": [
        {
            "title": "Здание мастерских, вид с улицы, 2008 год",
            "name": "42931-Intorist_grage2-683x1024.JPG"
        }
    ]
}