{
    "id": 501,
    "url": "https://moscow.drugiegoroda.ru/attractions/40276-ulica-1905-goda-stanciya-metro/",
    "title": "Улица 1905 года (станция метро)",
    "subtitle": "Cтанция Московского метрополитена. Расположена на Таганско-Краснопресненской линии между станциями «Беговая» и «Баррикадная»",
    "description": "Станция открыта 30 декабря 1972 года в составе участка «Баррикадная» — «Октябрьское поле».\nПроектное название станции — «Звенигородская». Проекты переименования: «Трёхгорка» (1991 год), «Ваганьково» (1992 год).\nНазвание станции — по близлежащей улице 1905 года, которая, в свою очередь, получила название в память о событиях декабря 1905 года.\nСеверный подземный вестибюль находится на улице 1905 года, южный наземный вестибюль в виде ротонды находится на площади Краснопресненской заставы, на пересечении улиц 1905 года, Красная Пресня и Пресненский вал. У южного вестибюля расположен монумент памяти революции 1905 года.\n«Улица 1905 года» — колонная трёхпролетная станция мелкого заложения. Сооружена из сборных конструкций по типовому проекту. На станции 2 ряда по 26 квадратных колонн с шагом 6,5 метров. Авторы проекта — Р. И. Погребной и Г. М. Суворов.\nПокрытие колонн — розовый мрамор различных тонов. Путевые стены облицованы серым мрамором и украшены фризом и металлическими вставками с изображениями цифр «1905» и факелов из анодированного под золото алюминия (художник — Ю. К. Королёв). Пол выложен серым гранитом.\n",
    "workingTime": "",
    "contacts": "",
    "price": "",
    "location": "",
    "photos": [
        {
            "title": "Вестибюль метро Улица 1905 года",
            "name": "61201-Ulitsa_1905_goda__1905__93005219-1024x768.jpg"
        },
        {
            "title": "Улица 1905 года",
            "name": "61200-Ulitsa_1905_goda__1905__88842525-768x1024.jpg"
        },
        {
            "title": "Станция метро улица 1905 года, общий вид",
            "name": "61199-Ulitsa_1905_Goda-1024x683.jpg"
        }
    ]
}