{
    "id": 249,
    "url": "https://moscow.drugiegoroda.ru/attractions/29035-stena-coya-na-arbate/",
    "title": "Стена Цоя на Арбате",
    "subtitle": "Стена Цоя, покрытая граффити, плакатами и надписями",
    "description": "Стена Цоя — стена дома № 37 по Арбату, выходящая в Кривоарбатский переулок Москвы, которую поклонники творчества Виктора Цоя исписали надписями «Кино», «Цой жив», цитатами из песен и признаниями в любви музыканту.\nСтена «появилась» в 1990 году, когда кто-то, после известия о гибели Виктора Цоя, высоко, через всю стену, вывел чёрным: «Сегодня погиб Виктор Цой». В ответ кто-то приписал: «Цой жив».\nС августа и до самых заморозков у «стены» постоянно дежурили подростки. Потом, после поминок на сорок дней, народу поубавилось, остались только самые стойкие. В дальнейшем появляются и другие надписи. Портрет Виктора, тот самый, что был выставлен на осеннем концерте его памяти, потом установили у стены.\nВадим Сидоров:\n«Для хипующей молодёжи стена была ещё и способом коммуникации, своеобразной «цыганской почтой». Здесь оставляли послания для друзей, с которыми не удалось увидеться, и назначали новые встречи. Теперь есть мобильный телефон. Но воспоминания о тех временах до́роги для поклонников группы «Кино»».\nУ поклонников творчества Цоя до сих пор принято оставлять в специальной пепельнице у Стены надломленную прикуренную сигарету. Там же планировалось установить памятник музыканту: босиком и сидящему на мотоцикле, но из-за протестов жителей окрестных домов и самих поклонников певца памятник установлен не был.\nМузыкальный обозреватель Никита Кривцов, в статье «Жив ли Рок-н-ролл?», опубликованной в официальном издании ЦК ВЛКСМ, дал следующую характеристику молодым людям, собирающимся у стены Цоя:\n«Они просто со всем пылом и чистотой юности оплакивают его гибель, собираясь вечерами у «стены» на Арбате, десятки раз в день слушая его песни, обклеивая стены своих комнат его фотографиями».\nБойкотируя выборы в Государственную думу 1995 года, 17 декабря, в день голосования, члены Право-Радикальной партии (ПРП) жгли у стены Цоя на Арбате избирательные бюллетени.\n\nВ 2006 году стена была закрашена группой неизвестных, но впоследствии восстановлена фанатами.\nВ 2009 году активисты молодёжного движения «Местные» и прокремлёвского движения «Молодая Гвардия» провели акцию в защиту «стены Цоя», направленную против желания властей закрасить надписи.\n",
    "workingTime": "24/7",
    "contacts": "37 Arbat street, Moscow",
    "price": "бесплатно",
    "location": "",
    "photos": [
        {
            "title": "Стена Цоя на Арбате",
            "name": "51940-The-Graffiti---1024x765.jpg"
        },
        {
            "title": " Стена Цоя, покрытая граффити, плакатами и надписями",
            "name": "51941-Tsoi_Wall_02-1024x768.JPG"
        }
    ]
}