{
    "id": 175,
    "url": "https://moscow.drugiegoroda.ru/attractions/31891-moskvoreckie-vorota/",
    "title": "Москворецкие ворота",
    "subtitle": "Несохранившиеся ворота Китайгородской стены",
    "description": "Также, как и Воскресенские ворота, были двухпролётными, но их верх завершал приземистый шатёр.\nОсновное название — по Москве-реке, также как и Водяные, а Спасские — по располагавшейся поблизости Спасской часовне.\nБыли построены в 1535–1538 годах в период Елены Глинской, правительнице при малолетнем Иване IV Грозном, как и вся Китайгородская стена. Архитектор — Петрок Мылый Фрязин.\nБыли снесены в 1813 году, а кирпичи использованы для починки стен Кремля.\nТакже был снесён участок, примыкающий к Кремлёвской стене, но участки в квартале Васильевского спуска были снесены при реконструкции в 1930-х годах.\n",
    "workingTime": "",
    "contacts": "",
    "price": "",
    "location": "",
    "photos": [
        {
            "title": "Спасские (Водяные) ворота Китай-города в XVII в.",
            "name": "57383-776-1024x680.jpg"
        },
        {
            "title": "Москворецкие ворота на картине А. М. Васнецова",
            "name": "57382-Vasnetsov_Moskvoretsky_most_Vodanye_Vorota-1024x829.jpg"
        }
    ]
}